{
    "description": "Private Cluster Disabled",
    "rationale": "A private cluster is a cluster that makes your master inaccessible from the public internet. In a private cluster, nodes do not have public IP addresses, so your workloads run in an environment that is isolated from the internet. Nodes have addressed only in the private RFC 1918 address space. Nodes and masters communicate with each other privately using VPC peering.",
    "compliance": [
        {
            "name": "CIS Google Cloud Platform Foundations",
            "version": "1.0.0",
            "reference": "7.15"
        },
        {
            "name": "CIS GKE Benchmark",
            "version": "1.0.0",
            "reference": "6.6.4"
        },
        {
            "name": "CIS GKE Benchmark",
            "version": "1.0.0",
            "reference": "6.6.5"
        }
    ],
    "references": [
        "https://www.cisecurity.org/benchmark/kubernetes/",
        "https://cloud.google.com/kubernetes-engine/docs/how-to/hardening-your-cluster#restrict_network_access_to_the_control_plane_and_nodes",
        "https://cloud.google.com/kubernetes-engine/docs/concepts/cis-benchmarks#default_values_on"
    ],
    "dashboard_name": "Clusters",
    "path": "kubernetesengine.projects.id.zones.id.clusters.id",
    "conditions": [
        "and",
        [
            "kubernetesengine.projects.id.zones.id.clusters.id.private_cluster_enabled",
            "false",
            ""
        ]
    ],
    "id_suffix": "private_cluster_disabled"
}
