{
    "description": "Secret Expiration Disabled",
    "rationale": "Secret expiration is disabled. As a result, compromised secrets could be used by potential attackers for a indefinite amount of time. Periodic secret rotation enforced with an appropriate secret expiration policy could help to mitigate this issue.",
    "remediation": "In the Azure console:<ol><li>Go to <samp>Key Vaults</samp></li> <li>For each key vault, go to <samp>Secrets</samp></li> <li>For all enabled secrets, ensure that an appropriate <samp>Expiration date</samp> is set</li></ol>",
    "compliance": [
        {
            "name": "CIS Microsoft Azure Foundations",
            "version": "1.2.0",
            "reference": "8.3"
        },
        {
            "name": "CIS Microsoft Azure Foundations",
            "version": "1.2.0",
            "reference": "8.4"
        }
    ],
    "references": [
        "https://learn.microsoft.com/en-us/azure/key-vault/secrets/about-secrets",
        "https://learn.microsoft.com/en-us/azure/key-vault/policy-reference",
        "https://learn.microsoft.com/en-us/security/benchmark/azure/security-controls-v3-data-protection#dp-6-use-a-secure-key-management-process"
    ],
    "dashboard_name": "Secrets",
    "display_path": "keyvault.subscriptions.id.vaults.id",
    "path": "keyvault.subscriptions.id.vaults.id.secrets.id",
    "conditions": [
        "and",
        [
            "keyvault.subscriptions.id.vaults.id.secrets.id.enabled",
            "true",
            ""
        ],
        [
            "keyvault.subscriptions.id.vaults.id.secrets.id.expires",
            "equal",
            "None"
        ]
    ],
    "id_suffix": "expires"
}